{
  "type": "stat",
  "title": "Calmar Ratio",
  "description": "Annualized return / |max_drawdown|. None when no drawdown.",
  "fieldConfig": {
    "defaults": {
      "unit": "none",
      "decimals": 2,
      "color": {
        "mode": "thresholds"
      },
      "thresholds": {
        "mode": "absolute",
        "steps": [
          {
            "color": "red",
            "value": null
          },
          {
            "color": "yellow",
            "value": 1.0
          },
          {
            "color": "green",
            "value": 3.0
          }
        ]
      }
    }
  },
  "options": {
    "colorMode": "value",
    "graphMode": "none",
    "reduceOptions": {
      "calcs": [
        "lastNotNull"
      ],
      "fields": "",
      "values": false
    },
    "text": {
      "titleSize": 16,
      "valueSize": 32
    },
    "textMode": "auto"
  },
  "targets": [
    {
      "refId": "A",
      "datasource": {
        "type": "core-datasource",
        "uid": "core-datasource"
      },
      "ref": "core-app/calmar_ratio"
    }
  ],
  "datasource": {
    "type": "core-datasource",
    "uid": "core-datasource"
  }
}
